{"market":"DOW","name":"Dow Jones Watcher","as_of":"2026-07-06T16:57:13.250515Z","cards":[{"symbol":"DJI","name":"Dow Jones Industrial Avg","group":"index","last":52910.1992,"change_1d_pct":0.02,"change_1w_pct":1.99,"change_1m_pct":4.39,"change_3m_pct":13.77,"trend":"flat","status":"DELAYED","source":"yahoo","as_of":"2026-07-06T13:30:00Z","is_proxy":false,"interpretation_en":"Dow Jones Industrial Avg rose 0.02% today; over the past month it is up (+4.4%).","interpretation_ko":"Dow Jones Industrial Avg 오늘 0.02% 상승 · 최근 1개월은 상승세(+4.4%)입니다."},{"symbol":"DIA","name":"SPDR Dow Jones ETF","group":"etf","last":528.43,"change_1d_pct":0.1,"change_1w_pct":2.06,"change_1m_pct":3.97,"change_3m_pct":13.63,"trend":"up","status":"DELAYED","source":"yahoo","as_of":"2026-07-06T13:30:00Z","is_proxy":false,"interpretation_en":"SPDR Dow Jones ETF rose 0.10% today; over the past month it is up (+4.0%).","interpretation_ko":"SPDR Dow Jones ETF 오늘 0.10% 상승 · 최근 1개월은 상승세(+4.0%)입니다."}],"metrics":[{"key":"r20","label_en":"1-month return","label_ko":"1개월 수익률","value":2.61,"unit":"%","status":"END_OF_DAY","hint_en":"","hint_ko":""},{"key":"r60","label_en":"3-month return","label_ko":"3개월 수익률","value":10.44,"unit":"%","status":"END_OF_DAY","hint_en":"","hint_ko":""},{"key":"r252","label_en":"1-year return","label_ko":"1년 수익률","value":18.94,"unit":"%","status":"END_OF_DAY","hint_en":"","hint_ko":""},{"key":"rsi14","label_en":"RSI(14)","label_ko":"RSI(14)","value":70.3,"unit":"","status":"END_OF_DAY","hint_en":"Above 70 overbought, below 30 oversold.","hint_ko":"70 이상 과매수, 30 이하 과매도."},{"key":"vol20","label_en":"Realized vol (20d, ann.)","label_ko":"실현변동성(20일, 연율)","value":13.2,"unit":"%","status":"END_OF_DAY","hint_en":"","hint_ko":""},{"key":"dd","label_en":"Distance from 52w high","label_ko":"52주 고점 대비","value":0.0,"unit":"%","status":"END_OF_DAY","hint_en":"","hint_ko":""},{"key":"mdd","label_en":"Max drawdown (2y)","label_ko":"최대낙폭(2년)","value":-16.37,"unit":"%","status":"END_OF_DAY","hint_en":"","hint_ko":""}],"diagnosis_en":"Dow Jones Watcher: the index is above its 200-day moving average, so the primary trend is still up. Momentum is 2.61% over 1 month and 10.44% over 3 months, and RSI 70 is overbought (>70) — stretched, prone to a pause. It is sitting at/near its 52-week high. The 200-day line is the key level to watch — losing it would flip the primary trend. Note: the Dow is price-weighted — high-priced members drive the index, not market cap.","diagnosis_ko":"Dow Jones Watcher: 지수는 200일 이동평균선 위에 있어 1차 추세는 상승입니다. 모멘텀은 1개월 2.61%, 3개월 10.44%, RSI 70는 과매수(70 초과)로 단기 과열·숨고르기 가능성이 있습니다. 현재가는 52주 고점 부근입니다. 200일선이 핵심 분기점으로, 이 선을 내주면 1차 추세가 전환됩니다. 참고: 다우는 가격가중 — 고가 종목이 지수를 좌우하며 시가총액이 아닙니다.","notes":[]}